<annotation verified="yes">
    <folder>Annotation</folder>
    <filename>186.jpg</filename>
    <path>Snooker-Shots-PascalVOC-export/Annotations/186.jpg</path>
    <source>
        <database>Unknown</database>
    </source>
    <size>
        <width>1280</width>
        <height>720</height>
        <depth>3</depth>
    </size>
    <segmented>0</segmented>
    <object>
    <name>yellow</name>
    <pose>Unspecified</pose>
    <truncated>0</truncated>
    <difficult>0</difficult>
    <bndbox>
        <xmin>536.6013766650808</xmin>
        <ymin>129.62437663586613</ymin>
        <xmax>558.0361709086584</xmax>
        <ymax>146.19287481162755</ymax>
    </bndbox>
</object><object>
    <name>brown</name>
    <pose>Unspecified</pose>
    <truncated>0</truncated>
    <difficult>0</difficult>
    <bndbox>
        <xmin>631.1094344671741</xmin>
        <ymin>131.57358547152603</ymin>
        <xmax>647.6726778068506</xmax>
        <ymax>147.16751640823287</ymax>
    </bndbox>
</object><object>
    <name>green</name>
    <pose>Unspecified</pose>
    <truncated>0</truncated>
    <difficult>0</difficult>
    <bndbox>
        <xmin>718.7973507373929</xmin>
        <ymin>128.6497350392608</ymin>
        <xmax>739.2578496669837</xmax>
        <ymax>149.11676242266816</ymax>
    </bndbox>
</object><object>
    <name>blue</name>
    <pose>Unspecified</pose>
    <truncated>0</truncated>
    <difficult>0</difficult>
    <bndbox>
        <xmin>630.1351391531874</xmin>
        <ymin>269.9695319935755</ymin>
        <xmax>650.5956380827782</xmax>
        <ymax>291.4111637948128</ymax>
    </bndbox>
</object><object>
    <name>red</name>
    <pose>Unspecified</pose>
    <truncated>0</truncated>
    <difficult>0</difficult>
    <bndbox>
        <xmin>719.7716460513797</xmin>
        <ymin>383.02539186429254</ymin>
        <xmax>740.2321449809705</xmax>
        <ymax>403.49238206892454</ymax>
    </bndbox>
</object><object>
    <name>red</name>
    <pose>Unspecified</pose>
    <truncated>0</truncated>
    <difficult>0</difficult>
    <bndbox>
        <xmin>786.0247680780209</xmin>
        <ymin>407.39087409779506</ymin>
        <xmax>806.4852670076117</xmax>
        <ymax>429.80711031686235</ymax>
    </bndbox>
</object><object>
    <name>white</name>
    <pose>Unspecified</pose>
    <truncated>0</truncated>
    <difficult>0</difficult>
    <bndbox>
        <xmin>763.615604186489</xmin>
        <ymin>402.51777765109455</ymin>
        <xmax>785.0504727640342</xmax>
        <ymax>425.90861828799177</ymax>
    </bndbox>
</object><object>
    <name>pink</name>
    <pose>Unspecified</pose>
    <truncated>0</truncated>
    <difficult>0</difficult>
    <bndbox>
        <xmin>627.2121788772597</xmin>
        <ymin>421.03552184129126</ymin>
        <xmax>650.5956380827782</xmax>
        <ymax>442.47719082130396</ymax>
    </bndbox>
</object><object>
    <name>red</name>
    <pose>Unspecified</pose>
    <truncated>0</truncated>
    <difficult>0</difficult>
    <bndbox>
        <xmin>594.0856178639391</xmin>
        <ymin>413.2385749623255</ymin>
        <xmax>611.6232308515699</xmax>
        <ymax>438.578661613658</ymax>
    </bndbox>
</object><object>
    <name>red</name>
    <pose>Unspecified</pose>
    <truncated>0</truncated>
    <difficult>0</difficult>
    <bndbox>
        <xmin>484.9629073501427</xmin>
        <ymin>357.6852680341847</ymin>
        <xmax>504.4491109657469</xmax>
        <ymax>378.15229541759203</ymax>
    </bndbox>
</object><object>
    <name>red</name>
    <pose>Unspecified</pose>
    <truncated>0</truncated>
    <difficult>0</difficult>
    <bndbox>
        <xmin>426.5042965033301</xmin>
        <ymin>431.75635633129764</ymin>
        <xmax>448.913460394862</xmax>
        <ymax>449.2994961036644</ymax>
    </bndbox>
</object><object>
    <name>red</name>
    <pose>Unspecified</pose>
    <truncated>0</truncated>
    <difficult>0</difficult>
    <bndbox>
        <xmin>623.3149232873453</xmin>
        <ymin>462.94418102593596</ymin>
        <xmax>643.7754965509039</xmax>
        <ymax>483.41117123056796</ymax>
    </bndbox>
</object>
</annotation>
