<annotation verified="yes">
    <folder>Annotation</folder>
    <filename>276.jpg</filename>
    <path>Snooker-Shots-PascalVOC-export/Annotations/276.jpg</path>
    <source>
        <database>Unknown</database>
    </source>
    <size>
        <width>1280</width>
        <height>720</height>
        <depth>3</depth>
    </size>
    <segmented>0</segmented>
    <object>
    <name>black</name>
    <pose>Unspecified</pose>
    <truncated>0</truncated>
    <difficult>0</difficult>
    <bndbox>
        <xmin>492.9989969909729</xmin>
        <ymin>243.35294509316512</ymin>
        <xmax>510.45942515045135</xmax>
        <ymax>260.8074983810996</ymax>
    </bndbox>
</object><object>
    <name>brown</name>
    <pose>Unspecified</pose>
    <truncated>0</truncated>
    <difficult>0</difficult>
    <bndbox>
        <xmin>592.6259246489468</xmin>
        <ymin>218.7112181964405</ymin>
        <xmax>610.086274448345</xmax>
        <ymax>232.0588039459392</ymax>
    </bndbox>
</object><object>
    <name>yellow</name>
    <pose>Unspecified</pose>
    <truncated>0</truncated>
    <difficult>0</difficult>
    <bndbox>
        <xmin>543.3259936058174</xmin>
        <ymin>261.834220682236</ymin>
        <xmax>558.7322122617853</xmax>
        <ymax>282.3689800405248</ymax>
    </bndbox>
</object><object>
    <name>blue</name>
    <pose>Unspecified</pose>
    <truncated>0</truncated>
    <difficult>0</difficult>
    <bndbox>
        <xmin>630.6278993229689</xmin>
        <ymin>360.401049935244</ymin>
        <xmax>648.0882491223671</xmax>
        <ymax>377.8556032231785</ymax>
    </bndbox>
</object><object>
    <name>red</name>
    <pose>Unspecified</pose>
    <truncated>0</truncated>
    <difficult>0</difficult>
    <bndbox>
        <xmin>737.4443643430291</xmin>
        <ymin>422.0053280101103</ymin>
        <xmax>757.9859892176529</xmax>
        <ymax>439.4598812980448</ymax>
    </bndbox>
</object><object>
    <name>white</name>
    <pose>Unspecified</pose>
    <truncated>0</truncated>
    <difficult>0</difficult>
    <bndbox>
        <xmin>821.6649949849548</xmin>
        <ymin>404.550813889121</ymin>
        <xmax>844.2608293630892</xmax>
        <ymax>426.1122955485461</ymax>
    </bndbox>
</object><object>
    <name>green</name>
    <pose>Unspecified</pose>
    <truncated>0</truncated>
    <difficult>0</difficult>
    <bndbox>
        <xmin>718.9568706118355</xmin>
        <ymin>264.91442675259026</ymin>
        <xmax>736.4172987713139</xmax>
        <ymax>282.3689800405248</ymax>
    </bndbox>
</object><object>
    <name>pink</name>
    <pose>Unspecified</pose>
    <truncated>0</truncated>
    <difficult>0</difficult>
    <bndbox>
        <xmin>628.5737681795385</xmin>
        <ymin>458.9679183551972</ymin>
        <xmax>649.1153930541624</xmax>
        <ymax>478.4759554123496</ymax>
    </bndbox>
</object>
</annotation>
