{
    "asset": {
        "format": "jpg",
        "id": "45897afc4498eb91dd343b7f41158903",
        "name": "133.jpg",
        "path": "file:C:/Users/u721848/Documents/CV/cv-snooker-analysis/training_data/133.jpg",
        "size": {
            "width": 1280,
            "height": 720
        },
        "state": 2,
        "type": 1,
        "predicted": true
    },
    "regions": [
        {
            "id": "yBpE1b8SN",
            "type": "RECTANGLE",
            "tags": [
                "blue"
            ],
            "boundingBox": {
                "height": 15.593893757931474,
                "width": 16.563317673644146,
                "left": 632.0837297811607,
                "top": 366.45685650975577
            },
            "points": [
                {
                    "x": 632.0837297811607,
                    "y": 366.45685650975577
                },
                {
                    "x": 648.6470474548049,
                    "y": 366.45685650975577
                },
                {
                    "x": 648.6470474548049,
                    "y": 382.0507502676872
                },
                {
                    "x": 632.0837297811607,
                    "y": 382.0507502676872
                }
            ]
        },
        {
            "id": "6Jre22PdZ",
            "type": "RECTANGLE",
            "tags": [
                "yellow"
            ],
            "boundingBox": {
                "height": 16.568535354536802,
                "width": 15.588948025689819,
                "left": 543.4215181969553,
                "top": 267.0456815613103
            },
            "points": [
                {
                    "x": 543.4215181969553,
                    "y": 267.0456815613103
                },
                {
                    "x": 559.010466222645,
                    "y": 267.0456815613103
                },
                {
                    "x": 559.010466222645,
                    "y": 283.6142169158471
                },
                {
                    "x": 543.4215181969553,
                    "y": 283.6142169158471
                }
            ]
        },
        {
            "id": "1e9ZWNuOK",
            "type": "RECTANGLE",
            "tags": [
                "white"
            ],
            "boundingBox": {
                "height": 14.619289340101524,
                "width": 16.563317673644146,
                "left": 477.168396170314,
                "top": 252.42639222120877
            },
            "points": [
                {
                    "x": 477.168396170314,
                    "y": 252.42639222120877
                },
                {
                    "x": 493.7317138439581,
                    "y": 252.42639222120877
                },
                {
                    "x": 493.7317138439581,
                    "y": 267.0456815613103
                },
                {
                    "x": 477.168396170314,
                    "y": 267.0456815613103
                }
            ]
        },
        {
            "id": "VKARGxKSY",
            "type": "RECTANGLE",
            "tags": [
                "pink"
            ],
            "boundingBox": {
                "height": 17.543139772366754,
                "width": 17.537612987630826,
                "left": 397.2749910799239,
                "top": 406.41623250118977
            },
            "points": [
                {
                    "x": 397.2749910799239,
                    "y": 406.41623250118977
                },
                {
                    "x": 414.8126040675547,
                    "y": 406.41623250118977
                },
                {
                    "x": 414.8126040675547,
                    "y": 423.9593722735565
                },
                {
                    "x": 397.2749910799239,
                    "y": 423.9593722735565
                }
            ]
        },
        {
            "id": "Ww54BxLWx",
            "type": "RECTANGLE",
            "tags": [
                "red"
            ],
            "boundingBox": {
                "height": 17.543176951142133,
                "width": 20.460498929590866,
                "left": 453.7850112987631,
                "top": 479.5126792016974
            },
            "points": [
                {
                    "x": 453.7850112987631,
                    "y": 479.5126792016974
                },
                {
                    "x": 474.24551022835396,
                    "y": 479.5126792016974
                },
                {
                    "x": 474.24551022835396,
                    "y": 497.0558561528395
                },
                {
                    "x": 453.7850112987631,
                    "y": 497.0558561528395
                }
            ]
        },
        {
            "id": "_aqK6zhpX",
            "type": "RECTANGLE",
            "tags": [
                "red"
            ],
            "boundingBox": {
                "height": 17.543139772366754,
                "width": 20.460573263558516,
                "left": 496.65459978591815,
                "top": 422.0101634378966
            },
            "points": [
                {
                    "x": 496.65459978591815,
                    "y": 422.0101634378966
                },
                {
                    "x": 517.1151730494767,
                    "y": 422.0101634378966
                },
                {
                    "x": 517.1151730494767,
                    "y": 439.5533032102634
                },
                {
                    "x": 496.65459978591815,
                    "y": 439.5533032102634
                }
            ]
        },
        {
            "id": "MdMlMoqA2",
            "type": "RECTANGLE",
            "tags": [
                "red"
            ],
            "boundingBox": {
                "height": 16.568572533312185,
                "width": 17.537538653663177,
                "left": 600.9058337297812,
                "top": 465.8679942794258
            },
            "points": [
                {
                    "x": 600.9058337297812,
                    "y": 465.8679942794258
                },
                {
                    "x": 618.4433723834443,
                    "y": 465.8679942794258
                },
                {
                    "x": 618.4433723834443,
                    "y": 482.43656681273796
                },
                {
                    "x": 600.9058337297812,
                    "y": 482.43656681273796
                }
            ]
        },
        {
            "id": "GG5g7ZZsb",
            "type": "RECTANGLE",
            "tags": [
                "black"
            ],
            "boundingBox": {
                "height": 17.54310259359137,
                "width": 18.511908301617506,
                "left": 631.1094344671741,
                "top": 535.0660233086136
            },
            "points": [
                {
                    "x": 631.1094344671741,
                    "y": 535.0660233086136
                },
                {
                    "x": 649.6213427687916,
                    "y": 535.0660233086136
                },
                {
                    "x": 649.6213427687916,
                    "y": 552.609125902205
                },
                {
                    "x": 631.1094344671741,
                    "y": 552.609125902205
                }
            ]
        },
        {
            "id": "15UaUYApM",
            "type": "RECTANGLE",
            "tags": [
                "red"
            ],
            "boundingBox": {
                "height": 20.71067848786485,
                "width": 20.70409134157945,
                "left": 655.2235965746908,
                "top": 500.7106598984772
            },
            "points": [
                {
                    "x": 655.2235965746908,
                    "y": 500.7106598984772
                },
                {
                    "x": 675.9276879162702,
                    "y": 500.7106598984772
                },
                {
                    "x": 675.9276879162702,
                    "y": 521.4213383863421
                },
                {
                    "x": 655.2235965746908,
                    "y": 521.4213383863421
                }
            ]
        },
        {
            "id": "aa3qPcpkT",
            "type": "RECTANGLE",
            "tags": [
                "red"
            ],
            "boundingBox": {
                "height": 22.41619904029188,
                "width": 15.588948025689819,
                "left": 680.7992388201712,
                "top": 471.715769501507
            },
            "points": [
                {
                    "x": 680.7992388201712,
                    "y": 471.715769501507
                },
                {
                    "x": 696.388186845861,
                    "y": 471.715769501507
                },
                {
                    "x": 696.388186845861,
                    "y": 494.1319685417989
                },
                {
                    "x": 680.7992388201712,
                    "y": 494.1319685417989
                }
            ]
        },
        {
            "id": "_JtlrKtbw",
            "type": "RECTANGLE",
            "tags": [
                "red"
            ],
            "boundingBox": {
                "height": 20.46699020463198,
                "width": 20.460498929590866,
                "left": 643.7754965509039,
                "top": 464.89338986159584
            },
            "points": [
                {
                    "x": 643.7754965509039,
                    "y": 464.89338986159584
                },
                {
                    "x": 664.2359954804948,
                    "y": 464.89338986159584
                },
                {
                    "x": 664.2359954804948,
                    "y": 485.36038006622783
                },
                {
                    "x": 643.7754965509039,
                    "y": 485.36038006622783
                }
            ]
        },
        {
            "id": "QQ7uc5wOK",
            "type": "RECTANGLE",
            "tags": [
                "red"
            ],
            "boundingBox": {
                "height": 16.568572533312185,
                "width": 13.64028306374881,
                "left": 629.1608438392008,
                "top": 464.89338986159584
            },
            "points": [
                {
                    "x": 629.1608438392008,
                    "y": 464.89338986159584
                },
                {
                    "x": 642.8011269029496,
                    "y": 464.89338986159584
                },
                {
                    "x": 642.8011269029496,
                    "y": 481.461962394908
                },
                {
                    "x": 629.1608438392008,
                    "y": 481.461962394908
                }
            ]
        }
    ],
    "version": "2.2.0"
}