{
    "asset": {
        "format": "jpg",
        "id": "901b6b3dd91e679054eb151802a83951",
        "name": "59.jpg",
        "path": "C:/Users/u721848/Documents/CV/cv-snooker-analysis/training_data/59.jpg",
        "size": {
            "width": 1280,
            "height": 720
        },
        "state": 2,
        "type": 1,
        "predicted": true
    },
    "regions": [
        {
            "id": "GCTDSz2je",
            "type": "RECTANGLE",
            "tags": [
                "green"
            ],
            "boundingBox": {
                "height": 177.1370298124207,
                "width": 176.59372026641293,
                "left": 427.47859181731684,
                "top": 366.7005076142132
            },
            "points": [
                {
                    "x": 427.47859181731684,
                    "y": 366.7005076142132
                },
                {
                    "x": 604.0723120837298,
                    "y": 366.7005076142132
                },
                {
                    "x": 604.0723120837298,
                    "y": 543.837537426634
                },
                {
                    "x": 427.47859181731684,
                    "y": 543.837537426634
                }
            ]
        },
        {
            "id": "mtQgUrFwz",
            "type": "RECTANGLE",
            "tags": [
                "white"
            ],
            "boundingBox": {
                "height": 180.3045685279188,
                "width": 181.2216787583254,
                "left": 522.9610192673643,
                "top": 173.4822446561707
            },
            "points": [
                {
                    "x": 522.9610192673643,
                    "y": 173.4822446561707
                },
                {
                    "x": 704.1826980256898,
                    "y": 173.4822446561707
                },
                {
                    "x": 704.1826980256898,
                    "y": 353.7868131840895
                },
                {
                    "x": 522.9610192673643,
                    "y": 353.7868131840895
                }
            ]
        }
    ],
    "version": "2.2.0"
}