{
    "asset": {
        "format": "jpg",
        "id": "8f2104cece5308bf018779f1b646f131",
        "name": "473.jpg",
        "path": "file:C:/Users/u721848/Documents/CV/cv-snooker-analysis/training_data/473.jpg",
        "size": {
            "width": 1280,
            "height": 720
        },
        "state": 2,
        "type": 1
    },
    "regions": [
        {
            "id": "ZNL-uoZWA",
            "type": "RECTANGLE",
            "tags": [
                "ball"
            ],
            "boundingBox": {
                "height": 14.399999999999999,
                "width": 16.314945524835988,
                "left": 536.232427366448,
                "top": 74.51998901367188
            },
            "points": [
                {
                    "x": 536.232427366448,
                    "y": 74.51998901367188
                },
                {
                    "x": 552.5473728912839,
                    "y": 74.51998901367188
                },
                {
                    "x": 552.5473728912839,
                    "y": 88.91998901367187
                },
                {
                    "x": 536.232427366448,
                    "y": 88.91998901367187
                }
            ]
        },
        {
            "id": "E7dJ7X3Jr",
            "type": "RECTANGLE",
            "tags": [
                "ball"
            ],
            "boundingBox": {
                "height": 21.12000732421875,
                "width": 19.194001874414244,
                "left": 538.1518714854733,
                "top": 141.71998901367186
            },
            "points": [
                {
                    "x": 538.1518714854733,
                    "y": 141.71998901367186
                },
                {
                    "x": 557.3458733598875,
                    "y": 141.71998901367186
                },
                {
                    "x": 557.3458733598875,
                    "y": 162.83999633789062
                },
                {
                    "x": 538.1518714854733,
                    "y": 162.83999633789062
                }
            ]
        },
        {
            "id": "u_oRfDcXJ",
            "type": "RECTANGLE",
            "tags": [
                "ball"
            ],
            "boundingBox": {
                "height": 15.3599853515625,
                "width": 21.113372774133083,
                "left": 626.4442508200561,
                "top": 142.6800109863281
            },
            "points": [
                {
                    "x": 626.4442508200561,
                    "y": 142.6800109863281
                },
                {
                    "x": 647.5576235941893,
                    "y": 142.6800109863281
                },
                {
                    "x": 647.5576235941893,
                    "y": 158.0399963378906
                },
                {
                    "x": 626.4442508200561,
                    "y": 158.0399963378906
                }
            ]
        },
        {
            "id": "kPLVspwcK",
            "type": "RECTANGLE",
            "tags": [
                "ball"
            ],
            "boundingBox": {
                "height": 22.07999267578125,
                "width": 21.113445993439548,
                "left": 627.4039362699156,
                "top": 276.11998901367184
            },
            "points": [
                {
                    "x": 627.4039362699156,
                    "y": 276.11998901367184
                },
                {
                    "x": 648.5173822633551,
                    "y": 276.11998901367184
                },
                {
                    "x": 648.5173822633551,
                    "y": 298.1999816894531
                },
                {
                    "x": 627.4039362699156,
                    "y": 298.1999816894531
                }
            ]
        },
        {
            "id": "OnrwWZ_3D",
            "type": "RECTANGLE",
            "tags": [
                "ball"
            ],
            "boundingBox": {
                "height": 23.039941406249998,
                "width": 21.113372774133083,
                "left": 534.3130564667291,
                "top": 446.04003295898434
            },
            "points": [
                {
                    "x": 534.3130564667291,
                    "y": 446.04003295898434
                },
                {
                    "x": 555.4264292408621,
                    "y": 446.04003295898434
                },
                {
                    "x": 555.4264292408621,
                    "y": 469.07997436523436
                },
                {
                    "x": 534.3130564667291,
                    "y": 469.07997436523436
                }
            ]
        },
        {
            "id": "s6lK9pnHz",
            "type": "RECTANGLE",
            "tags": [
                "ball"
            ],
            "boundingBox": {
                "height": 21.1200439453125,
                "width": 22.07313144329897,
                "left": 551.5876142221181,
                "top": 424.91998901367185
            },
            "points": [
                {
                    "x": 551.5876142221181,
                    "y": 424.91998901367185
                },
                {
                    "x": 573.660745665417,
                    "y": 424.91998901367185
                },
                {
                    "x": 573.660745665417,
                    "y": 446.04003295898434
                },
                {
                    "x": 551.5876142221181,
                    "y": 446.04003295898434
                }
            ]
        },
        {
            "id": "VVvgrEaw3",
            "type": "RECTANGLE",
            "tags": [
                "ball"
            ],
            "boundingBox": {
                "height": 19.2,
                "width": 23.032816893158387,
                "left": 627.4039362699156,
                "top": 416.28001098632814
            },
            "points": [
                {
                    "x": 627.4039362699156,
                    "y": 416.28001098632814
                },
                {
                    "x": 650.436753163074,
                    "y": 416.28001098632814
                },
                {
                    "x": 650.436753163074,
                    "y": 435.4800109863281
                },
                {
                    "x": 627.4039362699156,
                    "y": 435.4800109863281
                }
            ]
        },
        {
            "id": "8Va9ZKITf",
            "type": "RECTANGLE",
            "tags": [
                "ball"
            ],
            "boundingBox": {
                "height": 21.119970703125,
                "width": 20.153687324273662,
                "left": 656.194939081537,
                "top": 452.76000366210934
            },
            "points": [
                {
                    "x": 656.194939081537,
                    "y": 452.76000366210934
                },
                {
                    "x": 676.3486264058106,
                    "y": 452.76000366210934
                },
                {
                    "x": 676.3486264058106,
                    "y": 473.8799743652344
                },
                {
                    "x": 656.194939081537,
                    "y": 473.8799743652344
                }
            ]
        },
        {
            "id": "R6gzSPM83",
            "type": "RECTANGLE",
            "tags": [
                "ball"
            ],
            "boundingBox": {
                "height": 20.160058593749998,
                "width": 19.194001874414244,
                "left": 695.5426282802249,
                "top": 541.0799743652343
            },
            "points": [
                {
                    "x": 695.5426282802249,
                    "y": 541.0799743652343
                },
                {
                    "x": 714.7366301546391,
                    "y": 541.0799743652343
                },
                {
                    "x": 714.7366301546391,
                    "y": 561.2400329589843
                },
                {
                    "x": 695.5426282802249,
                    "y": 561.2400329589843
                }
            ]
        },
        {
            "id": "v9-5KmJK9",
            "type": "RECTANGLE",
            "tags": [
                "ball"
            ],
            "boundingBox": {
                "height": 28.799999999999997,
                "width": 21.113372774133083,
                "left": 969.0572282099344,
                "top": 499.8000183105469
            },
            "points": [
                {
                    "x": 969.0572282099344,
                    "y": 499.8000183105469
                },
                {
                    "x": 990.1706009840674,
                    "y": 499.8000183105469
                },
                {
                    "x": 990.1706009840674,
                    "y": 528.6000183105468
                },
                {
                    "x": 969.0572282099344,
                    "y": 528.6000183105468
                }
            ]
        }
    ],
    "version": "2.2.0"
}