<annotation verified="yes">
    <folder>Annotation</folder>
    <filename>112b1ee90956c958e9ffe85d0f6eff35079fd216.jpg</filename>
    <path>Snooker-2-PascalVOC-export/Annotations/112b1ee90956c958e9ffe85d0f6eff35079fd216.jpg</path>
    <source>
        <database>Unknown</database>
    </source>
    <size>
        <width>1280</width>
        <height>720</height>
        <depth>3</depth>
    </size>
    <segmented>0</segmented>
    <object>
    <name>ball</name>
    <pose>Unspecified</pose>
    <truncated>0</truncated>
    <difficult>0</difficult>
    <bndbox>
        <xmin>279.99249502108717</xmin>
        <ymin>566.0400329589844</ymin>
        <xmax>311.6626274015932</xmax>
        <ymax>591.0000183105469</ymax>
    </bndbox>
</object><object>
    <name>ball</name>
    <pose>Unspecified</pose>
    <truncated>0</truncated>
    <difficult>0</difficult>
    <bndbox>
        <xmin>540.0712423851921</xmin>
        <ymin>134.0399963378906</ymin>
        <xmax>561.1846151593252</xmax>
        <ymax>153.2399963378906</ymax>
    </bndbox>
</object><object>
    <name>ball</name>
    <pose>Unspecified</pose>
    <truncated>0</truncated>
    <difficult>0</difficult>
    <bndbox>
        <xmin>828.9409559512652</xmin>
        <ymin>85.07999267578124</ymin>
        <xmax>846.2155869259606</xmax>
        <ymax>107.15998535156248</ymax>
    </bndbox>
</object><object>
    <name>ball</name>
    <pose>Unspecified</pose>
    <truncated>0</truncated>
    <difficult>0</difficult>
    <bndbox>
        <xmin>632.2024367385192</xmin>
        <ymin>135.96000366210936</ymin>
        <xmax>651.3964386129334</xmax>
        <ymax>154.1999816894531</ymax>
    </bndbox>
</object><object>
    <name>ball</name>
    <pose>Unspecified</pose>
    <truncated>0</truncated>
    <difficult>0</difficult>
    <bndbox>
        <xmin>629.3233803889409</xmin>
        <ymin>277.0800109863281</ymin>
        <xmax>654.2755681818181</xmax>
        <ymax>295.31998901367183</ymax>
    </bndbox>
</object><object>
    <name>ball</name>
    <pose>Unspecified</pose>
    <truncated>0</truncated>
    <difficult>0</difficult>
    <bndbox>
        <xmin>757.9231343720712</xmin>
        <ymin>347.1600036621094</ymin>
        <xmax>781.915636715089</xmax>
        <ymax>370.1999816894531</ymax>
    </bndbox>
</object><object>
    <name>ball</name>
    <pose>Unspecified</pose>
    <truncated>0</truncated>
    <difficult>0</difficult>
    <bndbox>
        <xmin>666.7516254686035</xmin>
        <ymin>290.5199890136719</ymin>
        <xmax>686.9053860121836</xmax>
        <ymax>307.79998168945315</ymax>
    </bndbox>
</object><object>
    <name>ball</name>
    <pose>Unspecified</pose>
    <truncated>0</truncated>
    <difficult>0</difficult>
    <bndbox>
        <xmin>667.7113841377694</xmin>
        <ymin>448.91998901367185</ymin>
        <xmax>684.9859418931584</xmax>
        <ymax>471.96000366210933</ymax>
    </bndbox>
</object><object>
    <name>ball</name>
    <pose>Unspecified</pose>
    <truncated>0</truncated>
    <difficult>0</difficult>
    <bndbox>
        <xmin>673.4695700562323</xmin>
        <ymin>392.28001098632814</ymin>
        <xmax>698.4217578491096</xmax>
        <ymax>417.23999633789066</ymax>
    </bndbox>
</object><object>
    <name>ball</name>
    <pose>Unspecified</pose>
    <truncated>0</truncated>
    <difficult>0</difficult>
    <bndbox>
        <xmin>920.1124648547328</xmin>
        <ymin>440.27997436523435</ymin>
        <xmax>946.9840967666354</xmax>
        <ymax>460.4400329589844</ymax>
    </bndbox>
</object><object>
    <name>ball</name>
    <pose>Unspecified</pose>
    <truncated>0</truncated>
    <difficult>0</difficult>
    <bndbox>
        <xmin>777.1171362464854</xmin>
        <ymin>453.71998901367186</ymin>
        <xmax>796.3111381208996</xmax>
        <ymax>472.91998901367185</ymax>
    </bndbox>
</object><object>
    <name>ball</name>
    <pose>Unspecified</pose>
    <truncated>0</truncated>
    <difficult>0</difficult>
    <bndbox>
        <xmin>774.2380798969072</xmin>
        <ymin>481.56000366210935</ymin>
        <xmax>796.3111381208996</xmax>
        <ymax>503.64003295898436</ymax>
    </bndbox>
</object><object>
    <name>ball</name>
    <pose>Unspecified</pose>
    <truncated>0</truncated>
    <difficult>0</difficult>
    <bndbox>
        <xmin>606.2905634957825</xmin>
        <ymin>540.1199890136719</ymin>
        <xmax>628.363621719775</xmax>
        <ymax>563.1600036621094</ymax>
    </bndbox>
</object><object>
    <name>ball</name>
    <pose>Unspecified</pose>
    <truncated>0</truncated>
    <difficult>0</difficult>
    <bndbox>
        <xmin>479.6101071930646</xmin>
        <ymin>499.8000183105469</ymin>
        <xmax>503.6026095360824</xmax>
        <ymax>520.9199890136719</ymax>
    </bndbox>
</object><object>
    <name>ball</name>
    <pose>Unspecified</pose>
    <truncated>0</truncated>
    <difficult>0</difficult>
    <bndbox>
        <xmin>870.2080892689784</xmin>
        <ymin>522.8400329589844</ymin>
        <xmax>898.9990920805998</xmax>
        <ymax>548.7600036621094</ymax>
    </bndbox>
</object><object>
    <name>ball</name>
    <pose>Unspecified</pose>
    <truncated>0</truncated>
    <difficult>0</difficult>
    <bndbox>
        <xmin>807.827583177132</xmin>
        <ymin>478.67997436523433</ymin>
        <xmax>827.0215850515463</xmax>
        <ymax>498.84003295898435</ymax>
    </bndbox>
</object><object>
    <name>ball</name>
    <pose>Unspecified</pose>
    <truncated>0</truncated>
    <difficult>0</difficult>
    <bndbox>
        <xmin>625.4845653701967</xmin>
        <ymin>435.4800109863281</ymin>
        <xmax>646.5979381443298</xmax>
        <ymax>454.6799743652344</ymax>
    </bndbox>
</object>
</annotation>
