<annotation verified="yes">
    <folder>Annotation</folder>
    <filename>29.jpg</filename>
    <path>Snooker-2-PascalVOC-export/Annotations/29.jpg</path>
    <source>
        <database>Unknown</database>
    </source>
    <size>
        <width>1280</width>
        <height>720</height>
        <depth>3</depth>
    </size>
    <segmented>0</segmented>
    <object>
    <name>ball</name>
    <pose>Unspecified</pose>
    <truncated>0</truncated>
    <difficult>0</difficult>
    <bndbox>
        <xmin>538.1518714854733</xmin>
        <ymin>128.27999267578124</ymin>
        <xmax>556.3861146907217</xmax>
        <ymax>149.3999816894531</ymax>
    </bndbox>
</object><object>
    <name>ball</name>
    <pose>Unspecified</pose>
    <truncated>0</truncated>
    <difficult>0</difficult>
    <bndbox>
        <xmin>627.4039362699156</xmin>
        <ymin>130.2</ymin>
        <xmax>646.5979381443298</xmax>
        <ymax>148.43999633789062</ymax>
    </bndbox>
</object><object>
    <name>ball</name>
    <pose>Unspecified</pose>
    <truncated>0</truncated>
    <difficult>0</difficult>
    <bndbox>
        <xmin>720.4948892924085</xmin>
        <ymin>128.27999267578124</ymin>
        <xmax>737.7694470477975</xmax>
        <ymax>146.51998901367188</ymax>
    </bndbox>
</object><object>
    <name>ball</name>
    <pose>Unspecified</pose>
    <truncated>0</truncated>
    <difficult>0</difficult>
    <bndbox>
        <xmin>662.9128836691658</xmin>
        <ymin>244.43999633789062</ymin>
        <xmax>683.0665709934394</xmax>
        <ymax>263.63999633789064</ymax>
    </bndbox>
</object><object>
    <name>ball</name>
    <pose>Unspecified</pose>
    <truncated>0</truncated>
    <difficult>0</difficult>
    <bndbox>
        <xmin>630.2830658388003</xmin>
        <ymin>271.3199890136719</ymin>
        <xmax>650.436753163074</xmax>
        <ymax>289.5600036621094</ymax>
    </bndbox>
</object><object>
    <name>ball</name>
    <pose>Unspecified</pose>
    <truncated>0</truncated>
    <difficult>0</difficult>
    <bndbox>
        <xmin>462.3355494376757</xmin>
        <ymin>342.36000366210936</ymin>
        <xmax>481.52955131208995</xmax>
        <ymax>360.5999816894531</ymax>
    </bndbox>
</object><object>
    <name>ball</name>
    <pose>Unspecified</pose>
    <truncated>0</truncated>
    <difficult>0</difficult>
    <bndbox>
        <xmin>442.181862113402</xmin>
        <ymin>398.0399963378906</ymin>
        <xmax>466.1743644564198</xmax>
        <ymax>418.1999816894531</ymax>
    </bndbox>
</object><object>
    <name>ball</name>
    <pose>Unspecified</pose>
    <truncated>0</truncated>
    <difficult>0</difficult>
    <bndbox>
        <xmin>358.68791002811616</xmin>
        <ymin>415.3199890136719</ymin>
        <xmax>382.68041237113397</xmax>
        <ymax>440.2799743652344</ymax>
    </bndbox>
</object><object>
    <name>ball</name>
    <pose>Unspecified</pose>
    <truncated>0</truncated>
    <difficult>0</difficult>
    <bndbox>
        <xmin>624.5248799203373</xmin>
        <ymin>459.47997436523434</ymin>
        <xmax>642.7591231255857</xmax>
        <ymax>485.40001831054684</ymax>
    </bndbox>
</object><object>
    <name>ball</name>
    <pose>Unspecified</pose>
    <truncated>0</truncated>
    <difficult>0</difficult>
    <bndbox>
        <xmin>651.3964386129334</xmin>
        <ymin>427.7999816894531</ymin>
        <xmax>675.3889409559512</xmax>
        <ymax>448.91998901367185</ymax>
    </bndbox>
</object><object>
    <name>ball</name>
    <pose>Unspecified</pose>
    <truncated>0</truncated>
    <difficult>0</difficult>
    <bndbox>
        <xmin>602.4517484770383</xmin>
        <ymin>527.6400329589843</ymin>
        <xmax>623.5651212511714</xmax>
        <ymax>548.7600036621093</ymax>
    </bndbox>
</object><object>
    <name>ball</name>
    <pose>Unspecified</pose>
    <truncated>0</truncated>
    <difficult>0</difficult>
    <bndbox>
        <xmin>856.7722733130271</xmin>
        <ymin>573.7199890136718</ymin>
        <xmax>883.6439052249297</xmax>
        <ymax>605.4000183105468</ymax>
    </bndbox>
</object><object>
    <name>ball</name>
    <pose>Unspecified</pose>
    <truncated>0</truncated>
    <difficult>0</difficult>
    <bndbox>
        <xmin>629.3233803889409</xmin>
        <ymin>524.7600036621094</ymin>
        <xmax>653.3158827319587</xmax>
        <ymax>548.7600036621094</ymax>
    </bndbox>
</object>
</annotation>
