<annotation verified="yes">
    <folder>Annotation</folder>
    <filename>384.jpg</filename>
    <path>Snooker-2-PascalVOC-export/Annotations/384.jpg</path>
    <source>
        <database>Unknown</database>
    </source>
    <size>
        <width>1280</width>
        <height>720</height>
        <depth>3</depth>
    </size>
    <segmented>0</segmented>
    <object>
    <name>ball</name>
    <pose>Unspecified</pose>
    <truncated>0</truncated>
    <difficult>0</difficult>
    <bndbox>
        <xmin>539.1115569353327</xmin>
        <ymin>130.2</ymin>
        <xmax>557.3458733598875</xmax>
        <ymax>145.56000366210935</ymax>
    </bndbox>
</object><object>
    <name>ball</name>
    <pose>Unspecified</pose>
    <truncated>0</truncated>
    <difficult>0</difficult>
    <bndbox>
        <xmin>629.3233803889409</xmin>
        <ymin>131.15998535156248</ymin>
        <xmax>646.5979381443299</xmax>
        <ymax>144.5999816894531</ymax>
    </bndbox>
</object><object>
    <name>ball</name>
    <pose>Unspecified</pose>
    <truncated>0</truncated>
    <difficult>0</difficult>
    <bndbox>
        <xmin>719.5351306232427</xmin>
        <ymin>130.2</ymin>
        <xmax>737.7694470477975</xmax>
        <ymax>145.56000366210935</ymax>
    </bndbox>
</object><object>
    <name>ball</name>
    <pose>Unspecified</pose>
    <truncated>0</truncated>
    <difficult>0</difficult>
    <bndbox>
        <xmin>639.8800667760074</xmin>
        <ymin>174.36000366210936</ymin>
        <xmax>661.9531249999999</xmax>
        <ymax>196.43999633789062</ymax>
    </bndbox>
</object><object>
    <name>ball</name>
    <pose>Unspecified</pose>
    <truncated>0</truncated>
    <difficult>0</difficult>
    <bndbox>
        <xmin>630.2830658388003</xmin>
        <ymin>270.36000366210936</ymin>
        <xmax>650.436753163074</xmax>
        <ymax>290.5199890136719</ymax>
    </bndbox>
</object><object>
    <name>ball</name>
    <pose>Unspecified</pose>
    <truncated>0</truncated>
    <difficult>0</difficult>
    <bndbox>
        <xmin>462.3355494376757</xmin>
        <ymin>342.36000366210936</ymin>
        <xmax>481.52955131208995</xmax>
        <ymax>361.56000366210935</ymax>
    </bndbox>
</object><object>
    <name>ball</name>
    <pose>Unspecified</pose>
    <truncated>0</truncated>
    <difficult>0</difficult>
    <bndbox>
        <xmin>444.10123301312086</xmin>
        <ymin>398.0399963378906</ymin>
        <xmax>463.2952348875351</xmax>
        <ymax>416.28001098632814</ymax>
    </bndbox>
</object><object>
    <name>ball</name>
    <pose>Unspecified</pose>
    <truncated>0</truncated>
    <difficult>0</difficult>
    <bndbox>
        <xmin>515.1190545923149</xmin>
        <ymin>398.99998168945314</ymin>
        <xmax>538.1518714854733</xmax>
        <ymax>419.1600036621094</ymax>
    </bndbox>
</object><object>
    <name>ball</name>
    <pose>Unspecified</pose>
    <truncated>0</truncated>
    <difficult>0</difficult>
    <bndbox>
        <xmin>357.72822457825674</xmin>
        <ymin>412.4399963378906</ymin>
        <xmax>381.72072692127455</xmax>
        <ymax>434.5199890136718</ymax>
    </bndbox>
</object><object>
    <name>ball</name>
    <pose>Unspecified</pose>
    <truncated>0</truncated>
    <difficult>0</difficult>
    <bndbox>
        <xmin>653.3158827319587</xmin>
        <ymin>425.8800109863281</ymin>
        <xmax>670.5904404873477</xmax>
        <ymax>446.04003295898434</ymax>
    </bndbox>
</object><object>
    <name>ball</name>
    <pose>Unspecified</pose>
    <truncated>0</truncated>
    <difficult>0</difficult>
    <bndbox>
        <xmin>620.6860649015932</xmin>
        <ymin>458.5199890136719</ymin>
        <xmax>645.6382526944705</xmax>
        <ymax>483.4799743652344</ymax>
    </bndbox>
</object><object>
    <name>ball</name>
    <pose>Unspecified</pose>
    <truncated>0</truncated>
    <difficult>0</difficult>
    <bndbox>
        <xmin>628.363621719775</xmin>
        <ymin>523.8000183105469</ymin>
        <xmax>650.436753163074</xmax>
        <ymax>548.7600036621094</ymax>
    </bndbox>
</object>
</annotation>
