<annotation verified="yes">
    <folder>Annotation</folder>
    <filename>429.jpg</filename>
    <path>Snooker-2-PascalVOC-export/Annotations/429.jpg</path>
    <source>
        <database>Unknown</database>
    </source>
    <size>
        <width>1280</width>
        <height>720</height>
        <depth>3</depth>
    </size>
    <segmented>0</segmented>
    <object>
    <name>ball</name>
    <pose>Unspecified</pose>
    <truncated>0</truncated>
    <difficult>0</difficult>
    <bndbox>
        <xmin>537.1921128163074</xmin>
        <ymin>129.23999633789063</ymin>
        <xmax>558.3055588097469</xmax>
        <ymax>148.43999633789062</ymax>
    </bndbox>
</object><object>
    <name>ball</name>
    <pose>Unspecified</pose>
    <truncated>0</truncated>
    <difficult>0</difficult>
    <bndbox>
        <xmin>627.4039362699156</xmin>
        <ymin>131.15998535156248</ymin>
        <xmax>646.5979381443298</xmax>
        <ymax>149.3999816894531</ymax>
    </bndbox>
</object><object>
    <name>ball</name>
    <pose>Unspecified</pose>
    <truncated>0</truncated>
    <difficult>0</difficult>
    <bndbox>
        <xmin>718.5754451733833</xmin>
        <ymin>130.2</ymin>
        <xmax>734.8903906982192</xmax>
        <ymax>146.51998901367188</ymax>
    </bndbox>
</object><object>
    <name>ball</name>
    <pose>Unspecified</pose>
    <truncated>0</truncated>
    <difficult>0</difficult>
    <bndbox>
        <xmin>793.4320817713214</xmin>
        <ymin>73.5599853515625</ymin>
        <xmax>812.6260836457355</xmax>
        <ymax>95.63999633789062</ymax>
    </bndbox>
</object><object>
    <name>ball</name>
    <pose>Unspecified</pose>
    <truncated>0</truncated>
    <difficult>0</difficult>
    <bndbox>
        <xmin>691.7038864807872</xmin>
        <ymin>199.31998901367186</ymin>
        <xmax>713.7769447047797</xmax>
        <ymax>218.51998901367185</ymax>
    </bndbox>
</object><object>
    <name>ball</name>
    <pose>Unspecified</pose>
    <truncated>0</truncated>
    <difficult>0</difficult>
    <bndbox>
        <xmin>693.6232573805061</xmin>
        <ymin>262.6800109863281</ymin>
        <xmax>709.9381296860356</xmax>
        <ymax>279.9600036621094</ymax>
    </bndbox>
</object><object>
    <name>ball</name>
    <pose>Unspecified</pose>
    <truncated>0</truncated>
    <difficult>0</difficult>
    <bndbox>
        <xmin>629.3233803889409</xmin>
        <ymin>271.3199890136719</ymin>
        <xmax>647.5576235941893</xmax>
        <ymax>288.59998168945316</ymax>
    </bndbox>
</object><object>
    <name>ball</name>
    <pose>Unspecified</pose>
    <truncated>0</truncated>
    <difficult>0</difficult>
    <bndbox>
        <xmin>786.7141371836925</xmin>
        <ymin>405.71998901367186</ymin>
        <xmax>803.9887681583879</xmax>
        <ymax>426.8399963378906</ymax>
    </bndbox>
</object><object>
    <name>ball</name>
    <pose>Unspecified</pose>
    <truncated>0</truncated>
    <difficult>0</difficult>
    <bndbox>
        <xmin>424.9072311387066</xmin>
        <ymin>424.91998901367185</ymin>
        <xmax>448.8997334817244</xmax>
        <ymax>450.84003295898435</ymax>
    </bndbox>
</object><object>
    <name>ball</name>
    <pose>Unspecified</pose>
    <truncated>0</truncated>
    <difficult>0</difficult>
    <bndbox>
        <xmin>311.6626274015932</xmin>
        <ymin>533.4000183105469</ymin>
        <xmax>336.61481519447045</xmax>
        <ymax>557.4000183105469</ymax>
    </bndbox>
</object>
</annotation>
