<annotation verified="yes">
    <folder>Annotation</folder>
    <filename>480.jpg</filename>
    <path>Snooker-2-PascalVOC-export/Annotations/480.jpg</path>
    <source>
        <database>Unknown</database>
    </source>
    <size>
        <width>1280</width>
        <height>720</height>
        <depth>3</depth>
    </size>
    <segmented>0</segmented>
    <object>
    <name>ball</name>
    <pose>Unspecified</pose>
    <truncated>0</truncated>
    <difficult>0</difficult>
    <bndbox>
        <xmin>523.7563700796626</xmin>
        <ymin>146.51998901367188</ymin>
        <xmax>546.7891137535145</xmax>
        <ymax>168.59998168945313</ymax>
    </bndbox>
</object><object>
    <name>ball</name>
    <pose>Unspecified</pose>
    <truncated>0</truncated>
    <difficult>0</difficult>
    <bndbox>
        <xmin>629.3233803889409</xmin>
        <ymin>149.3999816894531</ymin>
        <xmax>649.4770677132145</xmax>
        <ymax>169.56000366210935</ymax>
    </bndbox>
</object><object>
    <name>ball</name>
    <pose>Unspecified</pose>
    <truncated>0</truncated>
    <difficult>0</difficult>
    <bndbox>
        <xmin>735.8500761480786</xmin>
        <ymin>148.43999633789062</ymin>
        <xmax>751.2052630037488</xmax>
        <ymax>168.59998168945313</ymax>
    </bndbox>
</object><object>
    <name>ball</name>
    <pose>Unspecified</pose>
    <truncated>0</truncated>
    <difficult>0</difficult>
    <bndbox>
        <xmin>630.2830658388003</xmin>
        <ymin>297.2399963378906</ymin>
        <xmax>649.4770677132145</xmax>
        <ymax>317.3999816894531</ymax>
    </bndbox>
</object><object>
    <name>ball</name>
    <pose>Unspecified</pose>
    <truncated>0</truncated>
    <difficult>0</difficult>
    <bndbox>
        <xmin>441.22210344423615</xmin>
        <ymin>261.71998901367186</ymin>
        <xmax>465.21460578725396</xmax>
        <ymax>286.6800109863281</ymax>
    </bndbox>
</object><object>
    <name>ball</name>
    <pose>Unspecified</pose>
    <truncated>0</truncated>
    <difficult>0</difficult>
    <bndbox>
        <xmin>631.2427512886597</xmin>
        <ymin>439.3199890136719</ymin>
        <xmax>653.3158827319587</xmax>
        <ymax>463.3199890136719</ymax>
    </bndbox>
</object><object>
    <name>ball</name>
    <pose>Unspecified</pose>
    <truncated>0</truncated>
    <difficult>0</difficult>
    <bndbox>
        <xmin>685.9456273430178</xmin>
        <ymin>485.40001831054684</ymin>
        <xmax>705.139629217432</xmax>
        <ymax>509.40001831054684</ymax>
    </bndbox>
</object><object>
    <name>ball</name>
    <pose>Unspecified</pose>
    <truncated>0</truncated>
    <difficult>0</difficult>
    <bndbox>
        <xmin>641.7994376757263</xmin>
        <ymin>470.04003295898434</ymin>
        <xmax>660.9934395501405</xmax>
        <ymax>489.24003295898433</ymax>
    </bndbox>
</object><object>
    <name>ball</name>
    <pose>Unspecified</pose>
    <truncated>0</truncated>
    <difficult>0</difficult>
    <bndbox>
        <xmin>620.6860649015932</xmin>
        <ymin>496.91998901367185</ymin>
        <xmax>639.8800667760074</xmax>
        <ymax>517.0799743652343</ymax>
    </bndbox>
</object><object>
    <name>ball</name>
    <pose>Unspecified</pose>
    <truncated>0</truncated>
    <difficult>0</difficult>
    <bndbox>
        <xmin>590.9353766401124</xmin>
        <ymin>517.0799743652343</ymin>
        <xmax>614.9278789831302</xmax>
        <ymax>540.1199890136718</ymax>
    </bndbox>
</object><object>
    <name>ball</name>
    <pose>Unspecified</pose>
    <truncated>0</truncated>
    <difficult>0</difficult>
    <bndbox>
        <xmin>651.3964386129334</xmin>
        <ymin>538.2000183105469</ymin>
        <xmax>673.4695700562323</xmax>
        <ymax>562.2000183105469</ymax>
    </bndbox>
</object><object>
    <name>ball</name>
    <pose>Unspecified</pose>
    <truncated>0</truncated>
    <difficult>0</difficult>
    <bndbox>
        <xmin>624.5248799203373</xmin>
        <ymin>547.8000183105469</ymin>
        <xmax>646.5979381443298</xmax>
        <ymax>571.8000183105469</ymax>
    </bndbox>
</object>
</annotation>
