<annotation verified="yes">
    <folder>Annotation</folder>
    <filename>536.jpg</filename>
    <path>Snooker-2-PascalVOC-export/Annotations/536.jpg</path>
    <source>
        <database>Unknown</database>
    </source>
    <size>
        <width>1280</width>
        <height>720</height>
        <depth>3</depth>
    </size>
    <segmented>0</segmented>
    <object>
    <name>ball</name>
    <pose>Unspecified</pose>
    <truncated>0</truncated>
    <difficult>0</difficult>
    <bndbox>
        <xmin>827.9812705014058</xmin>
        <ymin>92.75998535156249</ymin>
        <xmax>845.2559014761011</xmax>
        <ymax>113.87999267578124</ymax>
    </bndbox>
</object>
</annotation>
