<annotation verified="yes">
    <folder>Annotation</folder>
    <filename>603.jpg</filename>
    <path>Snooker-2-PascalVOC-export/Annotations/603.jpg</path>
    <source>
        <database>Unknown</database>
    </source>
    <size>
        <width>1280</width>
        <height>720</height>
        <depth>3</depth>
    </size>
    <segmented>0</segmented>
    <object>
    <name>ball</name>
    <pose>Unspecified</pose>
    <truncated>0</truncated>
    <difficult>0</difficult>
    <bndbox>
        <xmin>532.3936123477038</xmin>
        <ymin>120.6</ymin>
        <xmax>553.5070583411433</xmax>
        <ymax>144.59998168945313</ymax>
    </bndbox>
</object><object>
    <name>ball</name>
    <pose>Unspecified</pose>
    <truncated>0</truncated>
    <difficult>0</difficult>
    <bndbox>
        <xmin>722.4142601921274</xmin>
        <ymin>122.51998901367188</ymin>
        <xmax>740.6485766166821</xmax>
        <ymax>141.71998901367186</ymax>
    </bndbox>
</object><object>
    <name>ball</name>
    <pose>Unspecified</pose>
    <truncated>0</truncated>
    <difficult>0</difficult>
    <bndbox>
        <xmin>625.4845653701966</xmin>
        <ymin>265.56000366210935</ymin>
        <xmax>651.3964386129334</xmax>
        <ymax>291.59999999999997</ymax>
    </bndbox>
</object><object>
    <name>ball</name>
    <pose>Unspecified</pose>
    <truncated>0</truncated>
    <difficult>0</difficult>
    <bndbox>
        <xmin>651.3964386129334</xmin>
        <ymin>391.3199890136719</ymin>
        <xmax>675.3889409559512</xmax>
        <ymax>413.3999816894531</ymax>
    </bndbox>
</object><object>
    <name>ball</name>
    <pose>Unspecified</pose>
    <truncated>0</truncated>
    <difficult>0</difficult>
    <bndbox>
        <xmin>935.467651710403</xmin>
        <ymin>338.5199890136719</ymin>
        <xmax>956.5810977038425</xmax>
        <ymax>359.63999633789064</ymax>
    </bndbox>
</object><object>
    <name>ball</name>
    <pose>Unspecified</pose>
    <truncated>0</truncated>
    <difficult>0</difficult>
    <bndbox>
        <xmin>623.5651212511715</xmin>
        <ymin>528.6000183105468</ymin>
        <xmax>646.5979381443299</xmax>
        <ymax>553.5600036621094</ymax>
    </bndbox>
</object>
</annotation>
